subgraph_extractor/__init__.py
subgraph_extractor/cli.py
subgraph_extractor-1.0.1.dist-info/LICENSE
subgraph_extractor-1.0.1.dist-info/METADATA
subgraph_extractor-1.0.1.dist-info/WHEEL
subgraph_extractor-1.0.1.dist-info/entry_points.txt
subgraph_extractor-1.0.1.dist-info/top_level.txt
subgraph_extractor-1.0.1.dist-info/RECORD
