Metadata-Version: 2.1
Name: subgraph-extractor
Version: 1.0.1
Summary: Pull data from graph-node databases into parquet files
Home-page: http://github.com/cardstack/subgraph-extractor
Author: Ian Calvert
Author-email: ian.calvert@cardstack.com
License: None
License-File: LICENSE
Requires-Dist: click
Requires-Dist: pandas
Requires-Dist: pyyaml
Requires-Dist: sqlalchemy
Requires-Dist: psycopg2-binary
Requires-Dist: pyarrow >=9
Requires-Dist: simple-term-menu
Requires-Dist: tqdm
Requires-Dist: cloudpathlib[s3] >=0.9.0
Requires-Dist: deepdiff
Provides-Extra: dev
Requires-Dist: pytest ; extra == 'dev'
Requires-Dist: black ; extra == 'dev'
Requires-Dist: isort ; extra == 'dev'
Requires-Dist: pytest-pep8 ; extra == 'dev'
Requires-Dist: pytest-cov ; extra == 'dev'
Requires-Dist: pytest-postgresql ; extra == 'dev'
Requires-Dist: hypothesis ; extra == 'dev'
